vaping/__init__.py
vaping/asyncio_backport.py
vaping/cli.py
vaping/config/__init__.py
vaping/config/schema.py
vaping/daemon.py
vaping/io.py
vaping/plugins/__init__.py
vaping/plugins/command.py
vaping/plugins/fping.py
vaping/plugins/fping_mtr.py
vaping/plugins/graphite.py
vaping/plugins/logparse.py
vaping/plugins/prometheus.py
vaping/plugins/rrd.py
vaping/plugins/vodka.py
vaping/plugins/whisper.py
vaping/plugins/zeromq.py
vaping-1.5.4.dist-info/LICENSE
vaping-1.5.4.dist-info/METADATA
vaping-1.5.4.dist-info/WHEEL
vaping-1.5.4.dist-info/entry_points.txt
vaping-1.5.4.dist-info/RECORD
