Metadata-Version: 2.1
Name: vaping
Version: 1.5.4
Summary: vaping is a healthy alternative to smokeping!
Home-page: https://github.com/20c/vaping
License: Apache-2.0
Author: 20C
Author-email: code@20c.com
Requires-Python: >=3.8,<4.0
Classifier: Development Status :: 5 - Production/Stable
Classifier: Environment :: No Input/Output (Daemon)
Classifier: Intended Audience :: System Administrators
Classifier: Intended Audience :: Telecommunications Industry
Classifier: License :: OSI Approved :: Apache Software License
Classifier: Programming Language :: Python :: 3
Classifier: Programming Language :: Python :: 3.8
Classifier: Programming Language :: Python :: 3.9
Classifier: Programming Language :: Python :: 3.10
Classifier: Programming Language :: Python :: 3.11
Classifier: Programming Language :: Python :: 3.12
Classifier: Topic :: Internet
Classifier: Topic :: Software Development :: Libraries :: Python Modules
Classifier: Topic :: System :: Monitoring
Classifier: Topic :: System :: Networking :: Monitoring
Provides-Extra: all
Provides-Extra: graphite
Provides-Extra: prometheus
Provides-Extra: rrdtool
Provides-Extra: standalone
Provides-Extra: whisper
Provides-Extra: zeromq
Requires-Dist: Flask (>2,<2.2)
Requires-Dist: Werkzeug (>2,<2.1.0)
Requires-Dist: confu (>=1.7.1)
Requires-Dist: docutils (<=0.21)
Requires-Dist: graphsrv (>=2,<3) ; extra == "standalone" or extra == "all"
Requires-Dist: graphyte (>=1.4) ; extra == "graphite" or extra == "all"
Requires-Dist: munge[tomlkit,yaml] (>=1.2.0)
Requires-Dist: pid (>=3)
Requires-Dist: pluginmgr (>=1.2)
Requires-Dist: prometheus_client (>=0.11.0) ; extra == "prometheus" or extra == "all"
Requires-Dist: python-daemon (>=2)
Requires-Dist: pyzmq (>=15.3.0) ; extra == "zeromq" or extra == "all"
Requires-Dist: requests (>=2.19.1) ; extra == "graphite" or extra == "all"
Requires-Dist: rrdtool (>=0.1.14,<1) ; extra == "rrdtool" or extra == "all"
Requires-Dist: vodka (>=3.1,<4.0) ; extra == "standalone" or extra == "all"
Requires-Dist: whisper (>=0.9.15,<2) ; extra == "whisper" or extra == "all"
Project-URL: Repository, https://github.com/20c/vaping
